quick_draw_rps/__init__.py
quick_draw_rps/core.py
quick_draw_rps-0.1.1.dist-info/WHEEL
quick_draw_rps-0.1.1.dist-info/entry_points.txt
quick_draw_rps-0.1.1.dist-info/METADATA
quick_draw_rps-0.1.1.dist-info/RECORD
