Metadata-Version: 2.3
Name: quick-draw-rps
Version: 0.1.1
Summary: Rock Paper Scissors game as a CLI
Requires-Python: >=3.12
